kimchima/__init__.py
kimchima/cmds/__init__.py
kimchima/cmds/auto_cli.py
kimchima/cmds/kimchima_cli.py
kimchima/models/__init__.py
kimchima/pkg/__init__.py
kimchima/pkg/chat_template_factory.py
kimchima/pkg/cross_encoder_factory.py
kimchima/pkg/devices.py
kimchima/pkg/embedding_factory.py
kimchima/pkg/logging.py
kimchima/pkg/model_factory.py
kimchima/pkg/pipelines_factory.py
kimchima/pkg/streamer_factory.py
kimchima/pkg/tokenizer_factory.py
kimchima/tests/__init__.py
kimchima/tests/test_chat_template_factory.py
kimchima/tests/test_cross_encoder_factory.py
kimchima/tests/test_devices.py
kimchima/tests/test_dialog.py
kimchima/tests/test_downloadr.py
kimchima/tests/test_embedding_factory.py
kimchima/tests/test_model_factory.py
kimchima/tests/test_pipelines_factory.py
kimchima/utils/__init__.py
kimchima/utils/dialog.py
kimchima/utils/downloader.py
kimchima-0.5.4.dist-info/LICENSE
kimchima-0.5.4.dist-info/METADATA
kimchima-0.5.4.dist-info/WHEEL
kimchima-0.5.4.dist-info/RECORD
