Metadata-Version: 2.1
Name: kimchima
Version: 0.5.4
Summary: The collections of tools for ML model development.
Home-page: https://github.com/Aisuko/kimchi
License: Apache-2.0
Keywords: transformers,pytorch
Author: Aisuko
Author-email: urakiny@gmail.com
Requires-Python: >=3.11,<4.0
Classifier: License :: OSI Approved :: Apache Software License
Classifier: Programming Language :: Python :: 3
Classifier: Programming Language :: Python :: 3.11
Classifier: Programming Language :: Python :: 3.12
Requires-Dist: accelerate (==0.28.0)
Requires-Dist: datasets (==2.18.0)
Requires-Dist: torch (==2.2.2)
Requires-Dist: transformers (==4.39.2)
Project-URL: Repository, https://github.com/Aisuko/kimchi
